{
  "auto": true,
  "segments": [
    {
      "s": "10000",
      "e": "12920",
      "t": "open gam"
    },
    {
      "s": "13040",
      "e": "14890",
      "t": "star gam"
    },
    {
      "s": "14890",
      "e": "28420",
      "t": "[Music]"
    },
    {
      "s": "28960",
      "e": "30240",
      "t": "star"
    },
    {
      "s": "30240",
      "e": "49960",
      "t": "[Music]"
    },
    {
      "s": "58160",
      "e": "62480",
      "t": "good know hey I don't"
    },
    {
      "s": "71660",
      "e": "84079",
      "t": "[Music]"
    },
    {
      "s": "85079",
      "e": "87040",
      "t": "know"
    },
    {
      "s": "87040",
      "e": "91920",
      "t": "hey sexy lady"
    },
    {
      "s": "94320",
      "e": "97050",
      "t": "hey sexy"
    },
    {
      "s": "97050",
      "e": "117229",
      "t": "[Music]"
    },
    {
      "s": "118840",
      "e": "120920",
      "t": "lady"
    },
    {
      "s": "120920",
      "e": "131770",
      "t": "[Music]"
    },
    {
      "s": "141319",
      "e": "145080",
      "t": "know know"
    },
    {
      "s": "148840",
      "e": "151840",
      "t": "hey"
    },
    {
      "s": "153140",
      "e": "168879",
      "t": "[Music]"
    },
    {
      "s": "168879",
      "e": "172480",
      "t": "he sexy"
    },
    {
      "s": "173560",
      "e": "176159",
      "t": "lady star"
    },
    {
      "s": "176159",
      "e": "178840",
      "t": "hey sexy"
    },
    {
      "s": "178840",
      "e": "181840",
      "t": "lady"
    },
    {
      "s": "182650",
      "e": "185480",
      "t": "[Music]"
    },
    {
      "s": "185480",
      "e": "186740",
      "t": "baby"
    },
    {
      "s": "186740",
      "e": "191720",
      "t": "[Music]"
    },
    {
      "s": "191720",
      "e": "195200",
      "t": "baby baby"
    },
    {
      "s": "206879",
      "e": "208760",
      "t": "baby"
    },
    {
      "s": "208760",
      "e": "209870",
      "t": "hey"
    },
    {
      "s": "209870",
      "e": "215319",
      "t": "[Music]"
    },
    {
      "s": "215319",
      "e": "218319",
      "t": "seated"
    },
    {
      "s": "219520",
      "e": "223219",
      "t": "[Music]"
    },
    {
      "s": "238720",
      "e": "241720",
      "t": "star"
    },
    {
      "s": "245799",
      "e": "248760",
      "t": "openam"
    },
    {
      "s": "251159",
      "e": "254159",
      "t": "star"
    }
  ]
}